odoo/addons/event_session/README.rst
odoo/addons/event_session/__init__.py
odoo/addons/event_session/__manifest__.py
odoo/addons/event_session/i18n/es.po
odoo/addons/event_session/i18n/event_session.pot
odoo/addons/event_session/i18n/it.po
odoo/addons/event_session/i18n/nl.po
odoo/addons/event_session/i18n/pt.po
odoo/addons/event_session/migrations/14.0.1.0.0/noupdate_changes.xml
odoo/addons/event_session/migrations/14.0.1.0.0/post-migration.py
odoo/addons/event_session/migrations/14.0.1.0.0/pre-migration.py
odoo/addons/event_session/models/__init__.py
odoo/addons/event_session/models/event.py
odoo/addons/event_session/models/event_mail.py
odoo/addons/event_session/models/event_session.py
odoo/addons/event_session/readme/CONTRIBUTORS.rst
odoo/addons/event_session/readme/DESCRIPTION.rst
odoo/addons/event_session/readme/USAGE.rst
odoo/addons/event_session/security/event_session_security.xml
odoo/addons/event_session/security/ir.model.access.csv
odoo/addons/event_session/static/description/icon.png
odoo/addons/event_session/static/description/index.html
odoo/addons/event_session/tests/__init__.py
odoo/addons/event_session/tests/test_session.py
odoo/addons/event_session/views/event_session_view.xml
odoo/addons/event_session/views/event_view.xml
odoo/addons/event_session/wizards/__init__.py
odoo/addons/event_session/wizards/wizard_event_session.py
odoo/addons/event_session/wizards/wizard_event_session_view.xml
odoo14_addon_event_session-14.0.1.1.0.dist-info/METADATA
odoo14_addon_event_session-14.0.1.1.0.dist-info/WHEEL
odoo14_addon_event_session-14.0.1.1.0.dist-info/top_level.txt
odoo14_addon_event_session-14.0.1.1.0.dist-info/RECORD
